MANIFEST.in
README.rst
setup.py
stathat.py
stathat.egg-info/PKG-INFO
stathat.egg-info/SOURCES.txt
stathat.egg-info/dependency_links.txt
stathat.egg-info/requires.txt
stathat.egg-info/top_level.txt